gym_bwm/__init__.py
gym_bwm/envs/__init__.py
gym_bwm/envs/panda_env.py
gym_bwm-0.0.2.dist-info/METADATA
gym_bwm-0.0.2.dist-info/WHEEL
gym_bwm-0.0.2.dist-info/top_level.txt
gym_bwm-0.0.2.dist-info/RECORD
