Metadata-Version: 2.1
Name: gym-bwm
Version: 0.0.2
Summary: An OpenAI Gym Env for Panda
Home-page: UNKNOWN
License: UNKNOWN
Platform: UNKNOWN
Requires-Dist: gym
